universal_sitemap_loader/__init__.py
universal_sitemap_loader/__version__.py
universal_sitemap_loader/sitemapLoader.py
universal_sitemap_loader-1.0.1.dist-info/METADATA
universal_sitemap_loader-1.0.1.dist-info/WHEEL
universal_sitemap_loader-1.0.1.dist-info/licenses/LICENSE
universal_sitemap_loader-1.0.1.dist-info/RECORD
